ZetcodeQitaJiaochengChuyi/README.md
ZetcodeQitaJiaochengChuyi/__init__.py
ZetcodeQitaJiaochengChuyi/__main__.py
ZetcodeQitaJiaochengChuyi/file.epub
ZetcodeQitaJiaochengChuyi/index.html
ZetcodeQitaJiaochengChuyi/css/__init__.py
ZetcodeQitaJiaochengChuyi/css/annotations.css
ZetcodeQitaJiaochengChuyi/css/main.css
ZetcodeQitaJiaochengChuyi/css/normalize.css
ZetcodeQitaJiaochengChuyi/css/popup.css
ZetcodeQitaJiaochengChuyi/font/__init__.py
ZetcodeQitaJiaochengChuyi/font/fontello.eot
ZetcodeQitaJiaochengChuyi/font/fontello.svg
ZetcodeQitaJiaochengChuyi/font/fontello.ttf
ZetcodeQitaJiaochengChuyi/font/fontello.woff
ZetcodeQitaJiaochengChuyi/img/__init__.py
ZetcodeQitaJiaochengChuyi/img/annotator-glyph-sprite.png
ZetcodeQitaJiaochengChuyi/img/annotator-icon-sprite.png
ZetcodeQitaJiaochengChuyi/img/apple-touch-icon.png
ZetcodeQitaJiaochengChuyi/img/cancelfullscreen.png
ZetcodeQitaJiaochengChuyi/img/close.png
ZetcodeQitaJiaochengChuyi/img/fullscreen.png
ZetcodeQitaJiaochengChuyi/img/loader.gif
ZetcodeQitaJiaochengChuyi/img/menu-icon.png
ZetcodeQitaJiaochengChuyi/img/save.png
ZetcodeQitaJiaochengChuyi/img/saved.png
ZetcodeQitaJiaochengChuyi/img/settings-s.png
ZetcodeQitaJiaochengChuyi/img/settings.png
ZetcodeQitaJiaochengChuyi/img/star.png
ZetcodeQitaJiaochengChuyi/js/__init__.py
ZetcodeQitaJiaochengChuyi/js/epub.js
ZetcodeQitaJiaochengChuyi/js/epub.min.js
ZetcodeQitaJiaochengChuyi/js/epub.min.map
ZetcodeQitaJiaochengChuyi/js/hooks.min.js
ZetcodeQitaJiaochengChuyi/js/hooks.min.map
ZetcodeQitaJiaochengChuyi/js/reader.js
ZetcodeQitaJiaochengChuyi/js/reader.js.map
ZetcodeQitaJiaochengChuyi/js/reader.min.js
ZetcodeQitaJiaochengChuyi/js/reader.min.map
ZetcodeQitaJiaochengChuyi/js/hooks/__init__.py
ZetcodeQitaJiaochengChuyi/js/hooks/extensions/__init__.py
ZetcodeQitaJiaochengChuyi/js/hooks/extensions/highlight.js
ZetcodeQitaJiaochengChuyi/js/libs/__init__.py
ZetcodeQitaJiaochengChuyi/js/libs/jquery.min.js
ZetcodeQitaJiaochengChuyi/js/libs/localforage.min.js
zetcode_qita_jiaocheng_chuyi-2024.3.5.0.dist-info/METADATA
zetcode_qita_jiaocheng_chuyi-2024.3.5.0.dist-info/WHEEL
zetcode_qita_jiaocheng_chuyi-2024.3.5.0.dist-info/entry_points.txt
zetcode_qita_jiaocheng_chuyi-2024.3.5.0.dist-info/top_level.txt
zetcode_qita_jiaocheng_chuyi-2024.3.5.0.dist-info/RECORD
